{
  "firms": [
    {
      "id": "gk",
      "initials": "GK",
      "name": "M/S GK ENTERPRISES",
      "legalName": "GK Enterprises",
      "tradeName": "GK Enterprises",
      "gst": "09AKYPG8687K1ZW",
      "signature": "/signatures/sign.png",
      "address": "3/316, Gomti Nagar, Vishwas Khand, Lucknow, Lucknow, Uttar Pradesh, 226010",
      "phone": ["9910089804", "7379974538"],
      "email": "gkentlko@gmail.com",
      "quotationPrefix": "GK/NG",
      "bankDetails": {
        "bankName": "AXIS BANK",
        "accountNo": "924030004673222",
        "ifsc": "UTIB0001550",
        "branch": "GOMTI NAGAR, LUCKNOW"
      },
      "defaultTerms": {
        "payment": "100% against Delivery",
        "delivery": "8-10 days From Confirm Order"
      }
    },
    {
      "id": "swanvi",
      "initials": "SWANVI TECHNOLOGIES PRIVATE LIMITED",
      "name": "SWANVI TECHNOLOGIES PRIVATE LIMITED",
      "legalName": "SWANVI TECHNOLOGIES PRIVATE LIMITED",
      "tradeName": "SWANVI TECHNOLOGIES PRIVATE LIMITED",
      "gst": "09ABPCS8676R1ZS",
      "signature": "/signatures/sign-swanvi.png",
      "address": "A3/316,VISHWASH KHAND, GOMTI NAGAR, Lucknow, Lucknow, Uttar Pradesh, 226010",
      "phone": ["07379974538"],
      "email": "swanvitech@gmail.com",
      "quotationPrefix": "SV/NG",
      "bankDetails": {
        "bankName": "Union Bank",
        "accountNo": "521301010036884",
        "ifsc": "UBIN0552135",
        "branch": "GOMTI NAGAR"
      },
      "defaultTerms": {
        "payment": "100% against Delivery",
        "delivery": "5-7 days From Confirm Order"
      }
    },
    {
      "id": "GURUKRIPA",
      "initials": "GURUKRIPA",
      "name": "GURUKRIPA INFO SYSTEMS",
      "legalName": "GURUKRIPA INFO SYSTEMS",
      "tradeName": "GURUKRIPA INFO SYSTEMS",
      "gst": "05APGPA3564A1ZL",
      "signature": "/signatures/sign-saurabh.png",
      "address": "E/3, JK PURAM, CHOTI MUKHANI, HALDWANI, Nainital, Uttarakhand, 263139",
      "phone": ["08874800324"],
      "email": "gurukripainfos@gmail.com ",
      "quotationPrefix": "GK/QS",
      "bankDetails": {
        "bankName": "ICICI Bank ",
        "accountNo": "gurukripainfos@gmail.com ",
        "ifsc": "ICIC0007340",
        "branch": " Haldwani, Uttarakhand"
      },
      "defaultTerms": {
        "payment": "100% against Delivery",
        "delivery": "7-10 days From Confirm Order"
      }
    },
    {
      "id": "symgmatiq",
      "initials": "SY",
      "name": "SYGMATIQ TECHNOSOFT PRIVATE LIMITED",
      "legalName": "SYGMATIQ TECHNOSOFT PRIVATE LIMITED",
      "tradeName": "SYGMATIQ TECHNOSOFT PRIVATE LIMITED",
      "gst": "09ABNCS7432H1ZV",
      "signature": "/signatures/sign-symgmatiq.png",
      "address": "B-1603, ToweB, Green Arch, Sector-Techzone-IV,, Greater Noida (West), Noida, Gautambuddha Nagar, Uttar Pradesh, 201306",
      "phone": ["09717399612"],
      "email": "sygmatiq@gmail.com",
      "quotationPrefix": "SY/IN",
      "bankDetails": {
        "bankName": "ICICI Bank",
        "accountNo": "414605002041",
        "ifsc": "ICIC0004146",
        "branch": "CHERRY COUNTY"
      },
      "defaultTerms": {
        "payment": "100% advance",
        "delivery": "10-12 days From Confirm Order"
      }
    },
    {
      "id": "swati",
      "initials": "AS TECHNOLOGY",
      "name": "AS TECHNOLOGY",
      "legalName": "AS TECHNOLOGY",
      "tradeName": "AS TECHNOLOGY",
      "gst": "09CLMPG2501F1ZE",
      "signature": "/signatures/sign-swati.png",
      "address": "C-4 Tower,, Flat no-902, MI Rustle Court, Sector-6, Gomtinagar Extension, LUCKNOW, Lucknow, Uttar Pradesh, 226010",
      "phone": ["07379974538"],
      "email": " asteclko@gmail.com",
      "quotationPrefix": "ST/AS",
      "bankDetails": {
        "bankName": "ICICI Bank",
        "accountNo": "353105000184",
        "ifsc": "IFSC CODE",
        "branch": "Jankipuram, Lucknow"
      },
      "defaultTerms": {
        "payment": "50% against order, 50% against Delivery",
        "delivery": "3-5 days From Confirm Order"
      }
    },
    {
      "id": "ANKIT GOEL (HUF)",
      "initials": "ANJANI INFO SOLUTIONS",
      "name": "ANKIT GOEL (HUF)",
      "legalName": "ANKIT GOEL (HUF)",
      "tradeName": "ANJANI INFO SOLUTIONS",
      "gst": "09AAWHA2501C1ZM",
      "signature": "/signatures/sign-ankit.png",
      "address": "9th, FLAT NO-902, TOWER -C4, JACARANDA, Rustle Court, SECTOR-6, Gomti Nagar Vistar, Lucknow, Lucknow, Uttar Pradesh, 226010",
      "phone": ["06386850797"],
      "email": " anjaniinfos@gmail.com",
      "quotationPrefix": "AG/AI",
      "bankDetails": {
        "bankName": "SBI",
        "accountNo": "41354565043",
        "ifsc": "SBIN0003347",
        "branch": "ASHOK MARG"
      },
      "defaultTerms": {
        "payment": "100% against Delivery",
        "delivery": "7-8 days From Confirm Order"
      }
    }
  ]
}
